<?xml version = '1.0' encoding = 'UTF-8'?>
<!-- dbdrv: exec java oracle/jrad/tools/xml/importer XMLImporter.class java &phase=dat+24 checkfile:~PROD:~PATH:~FILE &fullpath:~PROD:~PATH:~FILE -username &un_apps -password &pw_apps -dbconnection &jdbc_db_addr  -userId "1" -rootPackage /oracle/apps/~PROD  -rootdir &fullpath:~PROD:mds:directory  -->
<page xmlns:jrad="http://xmlns.oracle.com/jrad" xmlns:oa="http://xmlns.oracle.com/oa" xmlns:ui="http://xmlns.oracle.com/uix/ui" version="9.0.3.8.12_1330" xml:lang="en-US" xmlns:user="http://xmlns.oracle.com/jrad/user" xmlns="http://xmlns.oracle.com/jrad" file-version="$Header$">
   <content>
      <oa:pageLayout id="pageLayoutRN" controllerClass="od.oracle.apps.xxom.xxomCustui.webui.xxomOrderHeaderAttPGCO" amDefName="od.oracle.apps.xxom.xxomCustui.server.xxomCustuiAM" windowTitle="Header Attributes" title="Header Attributes">
         <ui:corporateBranding>
            <oa:image id="corporateBrandingImage" source="/OA_MEDIA/FNDSSCORP.gif"/>
         </ui:corporateBranding>
         <ui:contents>
            <oa:tableLayout id="xxomOrderHeaderAttPGTBLLTRN" hAlign="center">
               <ui:contents>
                  <oa:rowLayout id="xxomOrderHeaderAttPGROW1">
                     <ui:contents>
                        <oa:cellFormat id="xxomOrderHeaderAttPGCELL1" rowSpan="2" vAlign="top" hAlign="left">
                           <ui:contents>
                              <oa:header id="xxomOrderHeaderAttPGHDR1" text="Order Details">
                                 <ui:contents>
                                    <oa:messageComponentLayout id="xxomOrderHeaderAttPGHDRRN">
                                       <ui:contents>
                                          <oa:messageStyledText id="OrderNumber1" dataType="NUMBER" prompt="Order Number" viewName="xxomOrderHeaderAttVO1" viewAttr="OrderNumber" styleClass="OraDataText"/>
                                          <oa:messageStyledText id="OrigSysDocumentRef" dataType="VARCHAR2" prompt="Orig Sys Document Ref" viewName="xxomOrderHeaderAttVO1" viewAttr="OrigSysDocumentRef" maximumLength="50" styleClass="OraDataText"/>
                                          <oa:messageStyledText id="OrderedDate" dataType="DATE" prompt="Order Date" viewName="xxomOrderHeaderAttVO1" viewAttr="OrderedDate" styleClass="OraDataText"/>
                                          <oa:messageStyledText id="OrderType" dataType="VARCHAR2" prompt="Order Type" viewName="xxomOrderHeaderAttVO1" viewAttr="OrderType" maximumLength="30" styleClass="OraDataText"/>
                                          <oa:messageStyledText id="FlowStatusCode" dataType="VARCHAR2" prompt="Status" viewName="xxomOrderHeaderAttVO1" viewAttr="FlowStatusCode" maximumLength="30" styleClass="OraDataText"/>
                                          <oa:messageStyledText id="OrderTotal" dataType="NUMBER" prompt="Order Total" viewName="xxomOrderHeaderAttVO1" viewAttr="OrderTotal" styleClass="OraDataText"/>
                                       </ui:contents>
                                    </oa:messageComponentLayout>
                                 </ui:contents>
                              </oa:header>
                           </ui:contents>
                        </oa:cellFormat>
                     </ui:contents>
                  </oa:rowLayout>
                  <oa:rowLayout id="xxomOrderHeaderAttPGROW2">
                     <ui:contents>
                        <oa:cellFormat id="xxomOrderHeaderAttPGCELL2" vAlign="top">
                           <ui:contents>
                              <oa:header id="xxomOrderHeaderAttPGHDR2" text="Delivery Details">
                                 <ui:contents>
                                    <oa:messageComponentLayout id="xxomOrderHeaderAttPGHDR2RN">
                                       <ui:contents>
                                          <oa:messageStyledText id="ShipToLocation" dataType="VARCHAR2" prompt="Ship To Location" viewName="xxomOrderHeaderAttVO1" viewAttr="ShipToLocation" maximumLength="40" styleClass="OraDataText"/>
                                          <oa:messageStyledText id="ShipToAddress1" dataType="VARCHAR2" prompt="Address" viewName="xxomOrderHeaderAttVO1" viewAttr="ShipToAddress1" maximumLength="240" styleClass="OraDataText"/>
                                          <oa:messageStyledText id="ShipToAddress2" dataType="VARCHAR2" viewName="xxomOrderHeaderAttVO1" viewAttr="ShipToAddress2" maximumLength="240" styleClass="OraDataText"/>
                                          <oa:messageStyledText id="ShipToAddress3" dataType="VARCHAR2" viewName="xxomOrderHeaderAttVO1" viewAttr="ShipToAddress3" maximumLength="240" styleClass="OraDataText"/>
                                          <oa:messageStyledText id="ShipToAddress4" dataType="VARCHAR2" viewName="xxomOrderHeaderAttVO1" viewAttr="ShipToAddress4" maximumLength="240" styleClass="OraDataText"/>
                                          <oa:messageStyledText id="ShipToAddress5" dataType="VARCHAR2" viewName="xxomOrderHeaderAttVO1" viewAttr="ShipToAddress5" maximumLength="246" styleClass="OraDataText"/>
                                          <oa:messageStyledText id="InvoiceToLocation" dataType="VARCHAR2" prompt="Invoice To Location" viewName="xxomOrderHeaderAttVO1" viewAttr="InvoiceToLocation" maximumLength="40" styleClass="OraDataText"/>
                                          <oa:messageStyledText id="InvoiceToAddress1" dataType="VARCHAR2" viewName="xxomOrderHeaderAttVO1" viewAttr="InvoiceToAddress1" maximumLength="240" styleClass="OraDataText" prompt="Address"/>
                                          <oa:messageStyledText id="InvoiceToAddress2" dataType="VARCHAR2" viewName="xxomOrderHeaderAttVO1" viewAttr="InvoiceToAddress2" maximumLength="240" styleClass="OraDataText"/>
                                          <oa:messageStyledText id="InvoiceToAddress3" dataType="VARCHAR2" viewName="xxomOrderHeaderAttVO1" viewAttr="InvoiceToAddress3" maximumLength="240" rendered="false" styleClass="OraDataText"/>
                                          <oa:messageStyledText id="InvoiceToAddress4" dataType="VARCHAR2" viewName="xxomOrderHeaderAttVO1" viewAttr="InvoiceToAddress4" maximumLength="240" rendered="false" styleClass="OraDataText"/>
                                          <oa:messageStyledText id="InvoiceToAddress5" dataType="VARCHAR2" viewName="xxomOrderHeaderAttVO1" viewAttr="InvoiceToAddress5" maximumLength="246" styleClass="OraDataText"/>
                                       </ui:contents>
                                    </oa:messageComponentLayout>
                                 </ui:contents>
                              </oa:header>
                           </ui:contents>
                        </oa:cellFormat>
                     </ui:contents>
                  </oa:rowLayout>
               </ui:contents>
            </oa:tableLayout>
            <oa:tableLayout id="xxomOrderHeaderAttPGAdtTBLLTRN" hAlign="center">
               <ui:contents>
                  <oa:rowLayout id="xxomOrderHeaderAttPGAdtROW1">
                     <ui:contents>
                        <oa:cellFormat id="xxomOrderHeaderAttPGAdtCELL1" rowSpan="2" vAlign="top">
                           <ui:contents>
                              <oa:header id="xxomOrderHeaderAttPGAdtHDR1" text="Customer Details">
                                 <ui:contents>
                                    <oa:messageComponentLayout id="xxomOrderHeaderAttPGAdtRN">
                                       <ui:contents>
                                          <oa:messageStyledText id="OrigCustName" dataType="VARCHAR2" prompt="Original Customer Name" viewName="xxomOrderHeaderAttVO1" viewAttr="OrigCustName" maximumLength="360" styleClass="OraDataText"/>
                                          <oa:messageStyledText id="CustContactName" dataType="VARCHAR2" prompt="Cust Contact Name" viewName="xxomOrderHeaderAttVO1" viewAttr="CustContactName" maximumLength="360" styleClass="OraDataText"/>
                                          <oa:messageStyledText id="CustPrefPhone" dataType="VARCHAR2" prompt="Customer Phone" viewName="xxomOrderHeaderAttVO1" viewAttr="CustPrefPhone" maximumLength="240" styleClass="OraDataText"/>
                                          <oa:messageStyledText id="CustPrefPhextn" dataType="VARCHAR2" prompt="Customer Ph Extn" viewName="xxomOrderHeaderAttVO1" viewAttr="CustPrefPhextn" maximumLength="240" styleClass="OraDataText"/>
                                          <oa:messageStyledText id="CustPrefEmail" dataType="VARCHAR2" prompt="Email" viewName="xxomOrderHeaderAttVO1" viewAttr="CustPrefEmail" maximumLength="240" styleClass="OraDataText"/>
                                          <oa:messageStyledText id="CustPrefFax" dataType="VARCHAR2" prompt="Fax" viewName="xxomOrderHeaderAttVO1" viewAttr="CustPrefFax" maximumLength="240" styleClass="OraDataText"/>
                                          <oa:messageStyledText id="SpcCardNumber" dataType="VARCHAR2" prompt="Spc Card Number" viewName="xxomOrderHeaderAttVO1" viewAttr="SpcCardNumber" maximumLength="20" styleClass="OraDataText"/>
                                          <oa:messageStyledText id="AdvantageCardNumber" dataType="VARCHAR2" prompt="Advantage Card Number" viewName="xxomOrderHeaderAttVO1" viewAttr="AdvantageCardNumber" maximumLength="240" styleClass="OraDataText"/>
                                       </ui:contents>
                                    </oa:messageComponentLayout>
                                 </ui:contents>
                              </oa:header>
                           </ui:contents>
                        </oa:cellFormat>
                     </ui:contents>
                  </oa:rowLayout>
                  <oa:rowLayout id="xxomOrderHeaderAttPGAdtROW2">
                     <ui:contents>
                        <oa:cellFormat id="xxomOrderHeaderAttPGAdtCELL2" vAlign="top">
                           <ui:contents>
                              <oa:header id="xxomOrderHeaderAttPGAdtHDR2" text="Source Details">
                                 <ui:contents>
                                    <oa:messageComponentLayout id="xxomOrderHeaderAttAdtRN1">
                                       <ui:contents>
                                          <oa:messageStyledText id="CreatedById" dataType="VARCHAR2" prompt="Order From" viewName="xxomOrderHeaderAttVO1" viewAttr="CreatedById" maximumLength="7" styleClass="OraDataText"/>
                                          <oa:messageStyledText id="CreatedByStoreId" dataType="NUMBER" prompt="Order Booked at(Store)" viewName="xxomOrderHeaderAttVO1" viewAttr="CreatedByStoreId" styleClass="OraDataText"/>
                                          <oa:messageStyledText id="PaidAtStoreId" dataType="NUMBER" prompt="Paid At(Store)" viewName="xxomOrderHeaderAttVO1" viewAttr="PaidAtStoreId" styleClass="OraDataText"/>
                                          <oa:messageStyledText id="OrderSourceName" dataType="VARCHAR2" prompt="Order Source" viewName="xxomOrderSerchVO1" viewAttr="Name" styleClass="OraDataText"/>
                                       </ui:contents>
                                    </oa:messageComponentLayout>
                                 </ui:contents>
                              </oa:header>
                           </ui:contents>
                        </oa:cellFormat>
                     </ui:contents>
                  </oa:rowLayout>
               </ui:contents>
            </oa:tableLayout>
            <oa:header id="xxomOrderHeaderAttAdtDtRN" text="Additional Details">
               <ui:contents>
                  <oa:table id="xxomOrderHeaderAttAdtDtTBL" width="100%">
                     <ui:contents>
                        <oa:messageStyledText id="OdOrderType" dataType="VARCHAR2" prompt="Legacy Order Type" viewName="xxomOrderHeaderAttVO1" viewAttr="OdOrderType" tipType="none" columns="10"/>
                        <oa:messageStyledText id="DeliveryCode" dataType="VARCHAR2" prompt="Dlvy Code" viewName="xxomOrderHeaderAttVO1" viewAttr="DeliveryCode" maximumLength="1"/>
                        <oa:messageStyledText id="DeliveryMethod" dataType="VARCHAR2" prompt="Dlvy Method" viewName="xxomOrderHeaderAttVO1" viewAttr="DeliveryMethod" maximumLength="4"/>
                        <oa:messageStyledText id="GiftFlag" dataType="VARCHAR2" prompt="Gift Flag" viewName="xxomOrderHeaderAttVO1" viewAttr="GiftFlag" maximumLength="1"/>
                        <oa:messageStyledText id="Brand" dataType="VARCHAR2" prompt="Brand" viewName="xxomOrderHeaderAttVO1" viewAttr="Brand" maximumLength="80"/>
                        <oa:messageStyledText id="Locale" dataType="VARCHAR2" prompt="Locale" viewName="xxomOrderHeaderAttVO1" viewAttr="Locale" maximumLength="80"/>
                        <oa:messageStyledText id="SalesrepId" dataType="NUMBER" prompt="Sales Rep Ref" viewName="xxomOrderHeaderAttVO1" viewAttr="SalesrepId" maximumLength="15" styleClass="string"/>
                     </ui:contents>
                  </oa:table>
                  <oa:spacer id="SpaceItem" height="10"/>
                  <oa:table id="xxomOrderHeaderAttAdtRN2" width="100%">
                     <ui:contents>
                        <oa:messageStyledText id="ReleaseNumber" dataType="VARCHAR2" prompt="Release NO" viewName="xxomOrderHeaderAttVO1" viewAttr="ReleaseNumber" maximumLength="240"/>
                        <oa:messageStyledText id="CostCenterDept" dataType="VARCHAR2" prompt="Cost Center Dept" viewName="xxomOrderHeaderAttVO1" viewAttr="CostCenterDept" maximumLength="240"/>
                        <oa:messageStyledText id="DeskDelAddr" dataType="VARCHAR2" prompt="Desk Del Addr" viewName="xxomOrderHeaderAttVO1" viewAttr="DeskDelAddr" maximumLength="240"/>
                        <oa:messageStyledText id="CustCarrAcctNo" dataType="VARCHAR2" prompt="Cust Carr Acct NO" viewName="xxomOrderHeaderAttVO1" viewAttr="CustCarrAcctNo"/>
                        <oa:messageStyledText id="CatalogSrcCd" dataType="VARCHAR2" prompt="Catalog Src Code" viewName="xxomOrderHeaderAttVO1" viewAttr="CatalogSrcCd" maximumLength="240"/>
                     </ui:contents>
                  </oa:table>
                  <oa:spacer id="spaceItem3" height="10"/>
                  <oa:table id="xxomOrderHeaderAttAdtRN3" width="100%">
                     <ui:contents>
                        <oa:messageStyledText id="Comments" viewName="xxomOrderHeaderAttVO1" viewAttr="Comments" prompt="Comments"/>
                     </ui:contents>
                  </oa:table>
                  <oa:link id="ReturnToSearchLink" text="Return To Search Page" destination="OA.jsp?page=/od/oracle/apps/xxom/xxomCustui/webui/xxomOrderSearchPG&amp;retainAM=Y"/>
                  <oa:spacer id="spaceItem1" width="5"/>
                  <oa:link id="PaymentsLink" text="Payments" destination="OA.jsp?page=/od/oracle/apps/xxom/xxomCustui/webui/xxomOrderPaymentsPG&amp;HeaderId={@HeaderId}&amp;retainAM=Y&amp;addBreadCrumb=Y"/>
                  <oa:spacer id="SpaceItem2" width="5"/>
                  <oa:link id="OrderLinesLink" text="Order Lines" destination="OA.jsp?page=/od/oracle/apps/xxom/xxomCustui/webui/xxomOrderLinesPG&amp;HeaderId={@HeaderId}&amp;retainAM=Y&amp;addBreadCrumb=Y"/>
               </ui:contents>
            </oa:header>
         </ui:contents>
      </oa:pageLayout>
   </content>
</page>
