<?xml version="1.0" encoding='windows-1252'?>
<!DOCTYPE ViewObject SYSTEM "jbo_03_01.dtd">

<ViewObject
   Name="ODSCSContactsVO"
   BindingStyle="Oracle"
   CustomQuery="true"
   RowClass="oracle.apps.fnd.framework.server.OAViewRowImpl"
   ComponentClass="od.oracle.apps.xxcrm.scs.fdk.server.ODSCSContactsVOImpl"
   MsgBundleClass="oracle.jbo.common.JboResourceBundle"
   UseGlueCode="false" >
   <SQLQuery><![CDATA[
select 
con.org_contact_id contact_id,
substr(pcon.party_name,0,instr(pcon.party_name,'-')-1) Contact_Full_Name,
substr(substr(pcon.party_name,0,instr(pcon.party_name,'-')-1),0,instr(substr(pcon.party_name,0,instr(pcon.party_name,'-')-1),' ')-1) first_name,
substr(substr(pcon.party_name,0,instr(pcon.party_name,'-')-1),instr(substr(pcon.party_name,0,instr(pcon.party_name,'-')-1),' ')+1) last_name,
pcon.primary_phone_country_code || '-' || pcon.primary_phone_area_code || '-' || pcon.primary_phone_number Phone,
pcon.email_address
from 
hz_parties porg, 
hz_relationships rel,
hz_org_contacts con,
hz_parties pcon
where porg.party_id = rel.subject_id
AND   con.party_relationship_id = rel.relationship_id
AND  rel.relationship_code = 'CONTACT'
AND  rel.direction_code = 'C'
AND  subject_type = 'ORGANIZATION'
AND pcon.party_id = rel.party_id
   ]]></SQLQuery>
   <DesignTime>
      <Attr Name="_version" Value="9.0.3.13.75" />
      <Attr Name="_CodeGenFlagNew" Value="36" />
   </DesignTime>
   <ViewAttribute
      Name="ContactId"
      IsPersistent="false"
      IsNotNull="true"
      Precision="15"
      Scale="0"
      Type="oracle.jbo.domain.Number"
      AliasName="CONTACT_ID"
      ColumnType="VARCHAR2"
      Expression="CONTACT_ID"
      SQLType="NUMERIC" >
      <DesignTime>
         <Attr Name="_DisplaySize" Value="22" />
      </DesignTime>
   </ViewAttribute>
   <ViewAttribute
      Name="ContactFullName"
      IsPersistent="false"
      Precision="1080"
      Type="java.lang.String"
      AliasName="CONTACT_FULL_NAME"
      ColumnType="VARCHAR2"
      Expression="CONTACT_FULL_NAME"
      SQLType="VARCHAR" >
      <DesignTime>
         <Attr Name="_DisplaySize" Value="1080" />
      </DesignTime>
   </ViewAttribute>
   <ViewAttribute
      Name="FirstName"
      IsPersistent="false"
      Precision="1080"
      Type="java.lang.String"
      AliasName="FIRST_NAME"
      ColumnType="VARCHAR2"
      Expression="FIRST_NAME"
      SQLType="VARCHAR" >
      <DesignTime>
         <Attr Name="_DisplaySize" Value="1080" />
      </DesignTime>
   </ViewAttribute>
   <ViewAttribute
      Name="LastName"
      IsPersistent="false"
      Precision="1080"
      Type="java.lang.String"
      AliasName="LAST_NAME"
      ColumnType="VARCHAR2"
      Expression="LAST_NAME"
      SQLType="VARCHAR" >
      <DesignTime>
         <Attr Name="_DisplaySize" Value="1080" />
      </DesignTime>
   </ViewAttribute>
   <ViewAttribute
      Name="Phone"
      IsPersistent="false"
      Precision="62"
      Type="java.lang.String"
      AliasName="PHONE"
      ColumnType="VARCHAR2"
      Expression="PHONE"
      SQLType="VARCHAR" >
      <DesignTime>
         <Attr Name="_DisplaySize" Value="62" />
      </DesignTime>
   </ViewAttribute>
   <ViewAttribute
      Name="EmailAddress"
      IsPersistent="false"
      Precision="2000"
      Type="java.lang.String"
      AliasName="EMAIL_ADDRESS"
      ColumnType="VARCHAR2"
      Expression="EMAIL_ADDRESS"
      SQLType="VARCHAR" >
      <DesignTime>
         <Attr Name="_DisplaySize" Value="2000" />
      </DesignTime>
   </ViewAttribute>
</ViewObject>
