<?xml version = '1.0' encoding = 'UTF-8'?>
<BPELSuitcase>
   <BPELProcess id="ProcessAJBFiles" src="ProcessAJBFiles.bpel">
      <partnerLinkBindings>
         <partnerLinkBinding name="client">
            <property name="wsdlLocation">ProcessAJBFiles.wsdl</property>
         </partnerLinkBinding>
         <partnerLinkBinding name="ServiceFileAJB998Read">
            <property name="wsdlLocation">ServiceFileAJB998Read.wsdl</property>
            <property name="Inbound_Path" type="LogicalDirectory"></property>
            <property name="retryInterval">60</property>
         </partnerLinkBinding>
         <partnerLinkBinding name="ServiceFileAJB996Read">
            <property name="wsdlLocation">ServiceFileAJB996Read.wsdl</property>
         </partnerLinkBinding>
         <partnerLinkBinding name="ServiceFileAJB999Read">
            <property name="wsdlLocation">ServiceFileAJB999Read.wsdl</property>
            <property name="Inbound_Path" type="LogicalDirectory"></property>
            <property name="retryInterval">60</property>
         </partnerLinkBinding>
         <partnerLinkBinding name="ODErrorLogger">
            <property name="wsdlLocation">http://chilsoa01d.na.odcorp.net:7778/orabpel/default/ODErrorLogger/ODErrorLogger?wsdl</property>
         </partnerLinkBinding>
         <partnerLinkBinding name="ServiceXX_CE_AJB_RECON_PKG">
            <property name="wsdlLocation">ServiceTableFileInsert.wsdl</property>
            <property name="retryInterval">60</property>
         </partnerLinkBinding>
         <partnerLinkBinding name="FileDelete">
            <property name="wsdlLocation">FileDelete.wsdl</property>
         </partnerLinkBinding>
         <partnerLinkBinding name="AJB999TableInsert">
            <property name="wsdlLocation">AJB999TableInsert.wsdl</property>
            <property name="idempotent">false</property>
         </partnerLinkBinding>
         <partnerLinkBinding name="AJB996TableInsert">
            <property name="wsdlLocation">AJB996TableInsert.wsdl</property>
            <property name="idempotent">false</property>
         </partnerLinkBinding>
         <partnerLinkBinding name="AJB998TableInsert">
            <property name="wsdlLocation">AJB998TableInsert.wsdl</property>
            <property name="idempotent">false</property>
         </partnerLinkBinding>
         <partnerLinkBinding name="Service_Duplicate_File_Check">
            <property name="wsdlLocation">Service_Duplicate_File_Check.wsdl</property>
            <property name="retryInterval">60</property>
         </partnerLinkBinding>
         <partnerLinkBinding name="ODTransactionLogger">
            <property name="wsdlLocation">http://chilsoa01d.na.odcorp.net:7778/orabpel/default/ODTransactionLogger/ODTransactionLogger?wsdl</property>
         </partnerLinkBinding>
         <partnerLinkBinding name="NotificationService">
            <property name="wsdlLocation">NotificationService.wsdl</property>
         </partnerLinkBinding>
         <partnerLinkBinding name="Service_BPEL_Record_File_Load">
            <property name="wsdlLocation">Service_BPEL_Record_File_Load.wsdl</property>
            <property name="retryInterval">60</property>
         </partnerLinkBinding>
         <partnerLinkBinding name="serviceCallCCProgram">
            <property name="wsdlLocation">serviceCallCCProgram.wsdl</property>
            <property name="retryInterval">60</property>
         </partnerLinkBinding>
      </partnerLinkBindings>
   </BPELProcess>
</BPELSuitcase>
